s3_upload_download/__init__.py
s3_upload_download/s3_transfers_utlits.py
s3_upload_download-0.0.4.dist-info/METADATA
s3_upload_download-0.0.4.dist-info/WHEEL
s3_upload_download-0.0.4.dist-info/top_level.txt
s3_upload_download-0.0.4.dist-info/RECORD
