Metadata-Version: 2.1
Name: s3-upload-download
Version: 0.0.4
Summary: Utility modules for the s3 upload and download tasks.
Author: Momataj Begum
Author-email: momataj.momo@gmail.com
License: UNKNOWN
Platform: UNKNOWN
Classifier: Programming Language :: Python :: 3
Classifier: License :: OSI Approved :: MIT License
Classifier: Operating System :: OS Independent
Requires-Python: >=3.6
Requires-Dist: boto3
